tabu/__init__.py
tabu/package_info.py
tabu/sampler.py
tabu/tabu_search.py
tabu/utils.py
dwave_tabu-0.5.0.dist-info/LICENSE
dwave_tabu-0.5.0.dist-info/METADATA
dwave_tabu-0.5.0.dist-info/WHEEL
dwave_tabu-0.5.0.dist-info/top_level.txt
dwave_tabu-0.5.0.dist-info/RECORD
