Metadata-Version: 2.1
Name: dwave-tabu
Version: 0.5.0
Summary: Optimized Tabu solver for QUBOs
Home-page: https://github.com/dwavesystems/dwave-tabu
Author: D-Wave Systems Inc.
Author-email: tools@dwavesys.com
License: Apache 2.0
Project-URL: Documentation, https://docs.ocean.dwavesys.com/en/stable/docs_tabu/sdk_index.html
Project-URL: Issue Tracker, https://github.com/dwavesystems/dwave-tabu/issues/
Project-URL: Source Code, https://github.com/dwavesystems/dwave-tabu/
Classifier: License :: OSI Approved :: Apache Software License
Classifier: Operating System :: OS Independent
Classifier: Development Status :: 4 - Beta
Classifier: Programming Language :: Python :: 3
Classifier: Programming Language :: Python :: 3 :: Only
Classifier: Programming Language :: Python :: 3.7
Classifier: Programming Language :: Python :: 3.8
Classifier: Programming Language :: Python :: 3.9
Classifier: Programming Language :: Python :: 3.10
Classifier: Programming Language :: Python :: 3.11
Classifier: Programming Language :: Python :: Implementation :: CPython
Requires-Python: >=3.7
License-File: LICENSE
